transmart/__init__.py
transmart/main.py
transmart/api/__init__.py
transmart/api/auth.py
transmart/api/commons.py
transmart/api/utils/__init__.py
transmart/api/utils/keycloak_role_manager.py
transmart/api/v1/__init__.py
transmart/api/v1/api.py
transmart/api/v1/highdim_pb2.py
transmart/api/v2/__init__.py
transmart/api/v2/api.py
transmart/api/v2/concept_search.py
transmart/api/v2/data_structures.py
transmart/api/v2/constraints/__init__.py
transmart/api/v2/constraints/atomic.py
transmart/api/v2/constraints/composite.py
transmart/api/v2/dashboard/__init__.py
transmart/api/v2/dashboard/dashboard.py
transmart/api/v2/dashboard/double_tiles.py
transmart/api/v2/dashboard/hypercube.py
transmart/api/v2/dashboard/single_tiles.py
transmart/api/v2/widgets/__init__.py
transmart/api/v2/widgets/concept_picker.py
transmart/api/v2/widgets/constraint_details.py
transmart/api/v2/widgets/shared.py
transmart-0.2.8.dist-info/LICENSE.txt
transmart-0.2.8.dist-info/METADATA
transmart-0.2.8.dist-info/WHEEL
transmart-0.2.8.dist-info/entry_points.txt
transmart-0.2.8.dist-info/top_level.txt
transmart-0.2.8.dist-info/RECORD
